[{"GEO":"Belgium","C_RESID":"Foreign country","Year":2010,"Average":59886.825},{"GEO":"Belgium","C_RESID":"Reporting country","Year":2010,"Average":48346.9333333333},{"GEO":"Bulgaria","C_RESID":"Foreign country","Year":2010,"Average":17322.8916666667},{"GEO":"Bulgaria","C_RESID":"Reporting country","Year":2010,"Average":18881.3583333333},{"GEO":"Czechia","C_RESID":"Foreign country","Year":2010,"Average":52783.3},{"GEO":"Czechia","C_RESID":"Reporting country","Year":2010,"Average":48982.35},{"GEO":"Denmark","C_RESID":"Foreign country","Year":2010,"Average":16556.95},{"GEO":"Denmark","C_RESID":"Reporting country","Year":2010,"Average":32111.6666666667},{"GEO":"Germany (until 1990 former territory of the FRG)","C_RESID":"Foreign country","Year":2010,"Average":223040.6083333333},{"GEO":"Germany (until 1990 former territory of the FRG)","C_RESID":"Reporting country","Year":2010,"Average":898297.6333333334},{"GEO":"Estonia","C_RESID":"Foreign country","Year":2010,"Average":13032.9333333333},{"GEO":"Estonia","C_RESID":"Reporting country","Year":2010,"Average":6981.7583333333},{"GEO":"Ireland","C_RESID":"Foreign country","Year":2010,"Average":30022.1916666667},{"GEO":"Ireland","C_RESID":"Reporting country","Year":2010,"Average":36066.6666666667},{"GEO":"Greece","C_RESID":"Foreign country","Year":2010,"Average":90244.225},{"GEO":"Greece","C_RESID":"Reporting country","Year":2010,"Average":75229.9083333333},{"GEO":"Spain","C_RESID":"Foreign country","Year":2010,"Average":361308.1416666667},{"GEO":"Spain","C_RESID":"Reporting country","Year":2010,"Average":465137.3333333333},{"GEO":"France","C_RESID":"Foreign country","Year":2010,"Average":487806.62},{"GEO":"France","C_RESID":"Reporting country","Year":2010,"Average":987908.1199999999},{"GEO":"Croatia","C_RESID":"Foreign country","Year":2010,"Average":55440.2666666667},{"GEO":"Croatia","C_RESID":"Reporting country","Year":2010,"Average":10557.475},{"GEO":"Italy","C_RESID":"Foreign country","Year":2010,"Average":364962.075},{"GEO":"Italy","C_RESID":"Reporting country","Year":2010,"Average":455741.6583333333},{"GEO":"Cyprus","C_RESID":"Foreign country","Year":2010,"Average":15119.4},{"GEO":"Cyprus","C_RESID":"Reporting country","Year":2010,"Average":5124.225},{"GEO":"Latvia","C_RESID":"Foreign country","Year":2010,"Average":7314.7833333333},{"GEO":"Latvia","C_RESID":"Reporting country","Year":2010,"Average":3614.7},{"GEO":"Lithuania","C_RESID":"Foreign country","Year":2010,"Average":6598.5083333333},{"GEO":"Lithuania","C_RESID":"Reporting country","Year":2010,"Average":4746.675},{"GEO":"Luxembourg","C_RESID":"Foreign country","Year":2010,"Average":6611.75},{"GEO":"Luxembourg","C_RESID":"Reporting country","Year":2010,"Average":403.675},{"GEO":"Hungary","C_RESID":"Foreign country","Year":2010,"Average":28215.075},{"GEO":"Hungary","C_RESID":"Reporting country","Year":2010,"Average":32651.675},{"GEO":"Malta","C_RESID":"Foreign country","Year":2010,"Average":9321.6333333333},{"GEO":"Malta","C_RESID":"Reporting country","Year":2010,"Average":1319.8916666667},{"GEO":"Netherlands","C_RESID":"Foreign country","Year":2010,"Average":90691.6666666667},{"GEO":"Netherlands","C_RESID":"Reporting country","Year":2010,"Average":159376.6666666667},{"GEO":"Austria","C_RESID":"Foreign country","Year":2010,"Average":160084.2166666667},{"GEO":"Austria","C_RESID":"Reporting country","Year":2010,"Average":87416.7166666667},{"GEO":"Poland","C_RESID":"Foreign country","Year":2010,"Average":34458.0833333333},{"GEO":"Poland","C_RESID":"Reporting country","Year":2010,"Average":136054.3833333333},{"GEO":"Portugal","C_RESID":"Foreign country","Year":2010,"Average":56302.95},{"GEO":"Portugal","C_RESID":"Reporting country","Year":2010,"Average":64058.5833333333},{"GEO":"Romania","C_RESID":"Foreign country","Year":2010,"Average":11191.2333333333},{"GEO":"Romania","C_RESID":"Reporting country","Year":2010,"Average":39109.8},{"GEO":"Slovenia","C_RESID":"Foreign country","Year":2010,"Average":16986.4833333333},{"GEO":"Slovenia","C_RESID":"Reporting country","Year":2010,"Average":10380.1},{"GEO":"Slovakia","C_RESID":"Foreign country","Year":2010,"Average":10941.825},{"GEO":"Slovakia","C_RESID":"Reporting country","Year":2010,"Average":17017.575},{"GEO":"Finland","C_RESID":"Foreign country","Year":2010,"Average":19324.4833333333},{"GEO":"Finland","C_RESID":"Reporting country","Year":2010,"Average":65708.4083333333},{"GEO":"Sweden","C_RESID":"Foreign country","Year":2010,"Average":41259.325},{"GEO":"Sweden","C_RESID":"Reporting country","Year":2010,"Average":154006.5083333333},{"GEO":"United Kingdom","C_RESID":"Foreign country","Year":2010,"Average":170699.8333333333},{"GEO":"United Kingdom","C_RESID":"Reporting country","Year":2010,"Average":562654.875},{"GEO":"Iceland","C_RESID":"Foreign country","Year":2010,"Average":9887.5833333333},{"GEO":"Iceland","C_RESID":"Reporting country","Year":2010,"Average":4480.4916666667},{"GEO":"Liechtenstein","C_RESID":"Foreign country","Year":2010,"Average":null},{"GEO":"Liechtenstein","C_RESID":"Reporting country","Year":2010,"Average":null},{"GEO":"Norway","C_RESID":"Foreign country","Year":2010,"Average":null},{"GEO":"Norway","C_RESID":"Reporting country","Year":2010,"Average":null},{"GEO":"Switzerland","C_RESID":"Foreign country","Year":2010,"Average":null},{"GEO":"Switzerland","C_RESID":"Reporting country","Year":2010,"Average":null},{"GEO":"Montenegro","C_RESID":"Foreign country","Year":2010,"Average":3989.05},{"GEO":"Montenegro","C_RESID":"Reporting country","Year":2010,"Average":879.55},{"GEO":"North Macedonia","C_RESID":"Foreign country","Year":2010,"Average":2157.85},{"GEO":"North Macedonia","C_RESID":"Reporting country","Year":2010,"Average":1781.925},{"GEO":"Albania","C_RESID":"Foreign country","Year":2010,"Average":null},{"GEO":"Albania","C_RESID":"Reporting country","Year":2010,"Average":null},{"GEO":"Serbia","C_RESID":"Foreign country","Year":2010,"Average":null},{"GEO":"Serbia","C_RESID":"Reporting country","Year":2010,"Average":null},{"GEO":"Turkey","C_RESID":"Foreign country","Year":2010,"Average":null},{"GEO":"Turkey","C_RESID":"Reporting country","Year":2010,"Average":null},{"GEO":"Kosovo (under United Nations Security Council Resolution 1244\/99)","C_RESID":"Foreign country","Year":2010,"Average":null},{"GEO":"Kosovo (under United Nations Security Council Resolution 1244\/99)","C_RESID":"Reporting country","Year":2010,"Average":null},{"GEO":"Belgium","C_RESID":"Foreign country","Year":2011,"Average":62137.25},{"GEO":"Belgium","C_RESID":"Reporting country","Year":2011,"Average":50809.5666666667},{"GEO":"Bulgaria","C_RESID":"Foreign country","Year":2011,"Average":20077.2416666667},{"GEO":"Bulgaria","C_RESID":"Reporting country","Year":2011,"Average":21064.5916666667},{"GEO":"Czechia","C_RESID":"Foreign country","Year":2011,"Average":55958.8916666667},{"GEO":"Czechia","C_RESID":"Reporting country","Year":2011,"Average":51530.375},{"GEO":"Denmark","C_RESID":"Foreign country","Year":2011,"Average":17910.875},{"GEO":"Denmark","C_RESID":"Reporting country","Year":2011,"Average":33382.9333333333},{"GEO":"Germany (until 1990 former territory of the FRG)","C_RESID":"Foreign country","Year":2011,"Average":235537.1333333334},{"GEO":"Germany (until 1990 former territory of the FRG)","C_RESID":"Reporting country","Year":2011,"Average":945635.4416666667},{"GEO":"Estonia","C_RESID":"Foreign country","Year":2011,"Average":15065.9916666667},{"GEO":"Estonia","C_RESID":"Reporting country","Year":2011,"Average":7650.15},{"GEO":"Ireland","C_RESID":"Foreign country","Year":2011,"Average":null},{"GEO":"Ireland","C_RESID":"Reporting country","Year":2011,"Average":null},{"GEO":"Greece","C_RESID":"Foreign country","Year":2011,"Average":100699.5},{"GEO":"Greece","C_RESID":"Reporting country","Year":2011,"Average":68597.15},{"GEO":"Spain","C_RESID":"Foreign country","Year":2011,"Average":397963.1416666667},{"GEO":"Spain","C_RESID":"Reporting country","Year":2011,"Average":461000.7},{"GEO":"France","C_RESID":"Foreign country","Year":2011,"Average":348193.5833333334},{"GEO":"France","C_RESID":"Reporting country","Year":2011,"Average":893062.65},{"GEO":"Croatia","C_RESID":"Foreign country","Year":2011,"Average":60308.975},{"GEO":"Croatia","C_RESID":"Reporting country","Year":2011,"Average":10698.9416666667},{"GEO":"Italy","C_RESID":"Foreign country","Year":2011,"Average":395506.7416666666},{"GEO":"Italy","C_RESID":"Reporting country","Year":2011,"Average":468858.8333333333},{"GEO":"Cyprus","C_RESID":"Foreign country","Year":2011,"Average":16228.725},{"GEO":"Cyprus","C_RESID":"Reporting country","Year":2011,"Average":4560.5583333333},{"GEO":"Latvia","C_RESID":"Foreign country","Year":2011,"Average":8860.7833333333},{"GEO":"Latvia","C_RESID":"Reporting country","Year":2011,"Average":4347.5166666667},{"GEO":"Lithuania","C_RESID":"Foreign country","Year":2011,"Average":7860.8333333333},{"GEO":"Lithuania","C_RESID":"Reporting country","Year":2011,"Average":5286.4666666667},{"GEO":"Luxembourg","C_RESID":"Foreign country","Year":2011,"Average":7282.9333333333},{"GEO":"Luxembourg","C_RESID":"Reporting country","Year":2011,"Average":508.6916666667},{"GEO":"Hungary","C_RESID":"Foreign country","Year":2011,"Average":30594.7666666667},{"GEO":"Hungary","C_RESID":"Reporting country","Year":2011,"Average":32622.8916666667},{"GEO":"Malta","C_RESID":"Foreign country","Year":2011,"Average":9995.5083333333},{"GEO":"Malta","C_RESID":"Reporting country","Year":2011,"Average":1199.775},{"GEO":"Netherlands","C_RESID":"Foreign country","Year":2011,"Average":94739.1666666667},{"GEO":"Netherlands","C_RESID":"Reporting country","Year":2011,"Average":161600.0},{"GEO":"Austria","C_RESID":"Foreign country","Year":2011,"Average":168171.0666666667},{"GEO":"Austria","C_RESID":"Reporting country","Year":2011,"Average":89389.7833333333},{"GEO":"Poland","C_RESID":"Foreign country","Year":2011,"Average":36746.25},{"GEO":"Poland","C_RESID":"Reporting country","Year":2011,"Average":142225.55},{"GEO":"Portugal","C_RESID":"Foreign country","Year":2011,"Average":60415.975},{"GEO":"Portugal","C_RESID":"Reporting country","Year":2011,"Average":62973.5},{"GEO":"Romania","C_RESID":"Foreign country","Year":2011,"Average":12622.2583333333},{"GEO":"Romania","C_RESID":"Reporting country","Year":2011,"Average":45728.0666666667},{"GEO":"Slovenia","C_RESID":"Foreign country","Year":2011,"Average":18528.6166666667},{"GEO":"Slovenia","C_RESID":"Reporting country","Year":2011,"Average":10819.3333333333},{"GEO":"Slovakia","C_RESID":"Foreign country","Year":2011,"Average":12064.1833333333},{"GEO":"Slovakia","C_RESID":"Reporting country","Year":2011,"Average":17408.1166666667},{"GEO":"Finland","C_RESID":"Foreign country","Year":2011,"Average":21836.55},{"GEO":"Finland","C_RESID":"Reporting country","Year":2011,"Average":67514.7083333333},{"GEO":"Sweden","C_RESID":"Foreign country","Year":2011,"Average":41715.2166666667},{"GEO":"Sweden","C_RESID":"Reporting country","Year":2011,"Average":158176.225},{"GEO":"United Kingdom","C_RESID":"Foreign country","Year":2011,"Average":177809.9833333333},{"GEO":"United Kingdom","C_RESID":"Reporting country","Year":2011,"Average":null},{"GEO":"Iceland","C_RESID":"Foreign country","Year":2011,"Average":11521.4},{"GEO":"Iceland","C_RESID":"Reporting country","Year":2011,"Average":4150.2916666667},{"GEO":"Liechtenstein","C_RESID":"Foreign country","Year":2011,"Average":null},{"GEO":"Liechtenstein","C_RESID":"Reporting country","Year":2011,"Average":null},{"GEO":"Norway","C_RESID":"Foreign country","Year":2011,"Average":null},{"GEO":"Norway","C_RESID":"Reporting country","Year":2011,"Average":null},{"GEO":"Switzerland","C_RESID":"Foreign country","Year":2011,"Average":null},{"GEO":"Switzerland","C_RESID":"Reporting country","Year":2011,"Average":null},{"GEO":"Montenegro","C_RESID":"Foreign country","Year":2011,"Average":10009.1583333333},{"GEO":"Montenegro","C_RESID":"Reporting country","Year":2011,"Average":1436.2916666667},{"GEO":"North Macedonia","C_RESID":"Foreign country","Year":2011,"Average":2702.075},{"GEO":"North Macedonia","C_RESID":"Reporting country","Year":2011,"Average":1729.8583333333},{"GEO":"Albania","C_RESID":"Foreign country","Year":2011,"Average":null},{"GEO":"Albania","C_RESID":"Reporting country","Year":2011,"Average":null},{"GEO":"Serbia","C_RESID":"Foreign country","Year":2011,"Average":null},{"GEO":"Serbia","C_RESID":"Reporting country","Year":2011,"Average":null},{"GEO":"Turkey","C_RESID":"Foreign country","Year":2011,"Average":null},{"GEO":"Turkey","C_RESID":"Reporting country","Year":2011,"Average":null},{"GEO":"Kosovo (under United Nations Security Council Resolution 1244\/99)","C_RESID":"Foreign country","Year":2011,"Average":null},{"GEO":"Kosovo (under United Nations Security Council Resolution 1244\/99)","C_RESID":"Reporting country","Year":2011,"Average":null},{"GEO":"Belgium","C_RESID":"Foreign country","Year":2012,"Average":63227.0333333333},{"GEO":"Belgium","C_RESID":"Reporting country","Year":2012,"Average":52836.5666666667},{"GEO":"Bulgaria","C_RESID":"Foreign country","Year":2012,"Average":21933.85},{"GEO":"Bulgaria","C_RESID":"Reporting country","Year":2012,"Average":23849.6},{"GEO":"Czechia","C_RESID":"Foreign country","Year":2012,"Average":63725.3666666667},{"GEO":"Czechia","C_RESID":"Reporting country","Year":2012,"Average":62098.1083333333},{"GEO":"Denmark","C_RESID":"Foreign country","Year":2012,"Average":18602.15},{"GEO":"Denmark","C_RESID":"Reporting country","Year":2012,"Average":33745.45},{"GEO":"Germany (until 1990 former territory of the FRG)","C_RESID":"Foreign country","Year":2012,"Average":252762.8583333333},{"GEO":"Germany (until 1990 former territory of the FRG)","C_RESID":"Reporting country","Year":2012,"Average":974727.0916666666},{"GEO":"Estonia","C_RESID":"Foreign country","Year":2012,"Average":15612.6583333333},{"GEO":"Estonia","C_RESID":"Reporting country","Year":2012,"Average":8053.1333333333},{"GEO":"Ireland","C_RESID":"Foreign country","Year":2012,"Average":17938.8833333333},{"GEO":"Ireland","C_RESID":"Reporting country","Year":2012,"Average":65137.2},{"GEO":"Greece","C_RESID":"Foreign country","Year":2012,"Average":93587.6333333333},{"GEO":"Greece","C_RESID":"Reporting country","Year":2012,"Average":58179.2166666667},{"GEO":"Spain","C_RESID":"Foreign country","Year":2012,"Average":400838.7416666666},{"GEO":"Spain","C_RESID":"Reporting country","Year":2012,"Average":435904.4166666667},{"GEO":"France","C_RESID":"Foreign country","Year":2012,"Average":353402.2333333333},{"GEO":"France","C_RESID":"Reporting country","Year":2012,"Average":888914.925},{"GEO":"Croatia","C_RESID":"Foreign country","Year":2012,"Average":84489.1333333333},{"GEO":"Croatia","C_RESID":"Reporting country","Year":2012,"Average":11707.975},{"GEO":"Italy","C_RESID":"Foreign country","Year":2012,"Average":406154.7916666666},{"GEO":"Italy","C_RESID":"Reporting country","Year":2012,"Average":458288.1833333333},{"GEO":"Cyprus","C_RESID":"Foreign country","Year":2012,"Average":16843.1583333333},{"GEO":"Cyprus","C_RESID":"Reporting country","Year":2012,"Average":4241.425},{"GEO":"Latvia","C_RESID":"Foreign country","Year":2012,"Average":9135.6166666667},{"GEO":"Latvia","C_RESID":"Reporting country","Year":2012,"Average":4570.7},{"GEO":"Lithuania","C_RESID":"Foreign country","Year":2012,"Average":9377.8166666667},{"GEO":"Lithuania","C_RESID":"Reporting country","Year":2012,"Average":7101.5666666667},{"GEO":"Luxembourg","C_RESID":"Foreign country","Year":2012,"Average":7920.175},{"GEO":"Luxembourg","C_RESID":"Reporting country","Year":2012,"Average":593.7666666667},{"GEO":"Hungary","C_RESID":"Foreign country","Year":2012,"Average":34445.2},{"GEO":"Hungary","C_RESID":"Reporting country","Year":2012,"Average":38402.5},{"GEO":"Malta","C_RESID":"Foreign country","Year":2012,"Average":9966.1416666667},{"GEO":"Malta","C_RESID":"Reporting country","Year":2012,"Average":1292.05},{"GEO":"Netherlands","C_RESID":"Foreign country","Year":2012,"Average":96946.525},{"GEO":"Netherlands","C_RESID":"Reporting country","Year":2012,"Average":162641.65},{"GEO":"Austria","C_RESID":"Foreign country","Year":2012,"Average":176764.35},{"GEO":"Austria","C_RESID":"Reporting country","Year":2012,"Average":92616.0333333333},{"GEO":"Poland","C_RESID":"Foreign country","Year":2012,"Average":41494.1166666667},{"GEO":"Poland","C_RESID":"Reporting country","Year":2012,"Average":147134.1166666667},{"GEO":"Portugal","C_RESID":"Foreign country","Year":2012,"Average":62527.1},{"GEO":"Portugal","C_RESID":"Reporting country","Year":2012,"Average":59517.5916666667},{"GEO":"Romania","C_RESID":"Foreign country","Year":2012,"Average":13778.0083333333},{"GEO":"Romania","C_RESID":"Reporting country","Year":2012,"Average":50000.1},{"GEO":"Slovenia","C_RESID":"Foreign country","Year":2012,"Average":17415.625},{"GEO":"Slovenia","C_RESID":"Reporting country","Year":2012,"Average":9272.2416666667},{"GEO":"Slovakia","C_RESID":"Foreign country","Year":2012,"Average":12589.1583333333},{"GEO":"Slovakia","C_RESID":"Reporting country","Year":2012,"Average":18497.1916666667},{"GEO":"Finland","C_RESID":"Foreign country","Year":2012,"Average":23160.4333333333},{"GEO":"Finland","C_RESID":"Reporting country","Year":2012,"Average":67524.4416666667},{"GEO":"Sweden","C_RESID":"Foreign country","Year":2012,"Average":41198.425},{"GEO":"Sweden","C_RESID":"Reporting country","Year":2012,"Average":157756.0416666667},{"GEO":"United Kingdom","C_RESID":"Foreign country","Year":2012,"Average":170521.6},{"GEO":"United Kingdom","C_RESID":"Reporting country","Year":2012,"Average":693436.3},{"GEO":"Iceland","C_RESID":"Foreign country","Year":2012,"Average":13575.325},{"GEO":"Iceland","C_RESID":"Reporting country","Year":2012,"Average":4331.2666666667},{"GEO":"Liechtenstein","C_RESID":"Foreign country","Year":2012,"Average":519.85},{"GEO":"Liechtenstein","C_RESID":"Reporting country","Year":2012,"Average":18.7},{"GEO":"Norway","C_RESID":"Foreign country","Year":2012,"Average":36457.3666666667},{"GEO":"Norway","C_RESID":"Reporting country","Year":2012,"Average":116485.2416666667},{"GEO":"Switzerland","C_RESID":"Foreign country","Year":2012,"Average":null},{"GEO":"Switzerland","C_RESID":"Reporting country","Year":2012,"Average":null},{"GEO":"Montenegro","C_RESID":"Foreign country","Year":2012,"Average":10534.6916666667},{"GEO":"Montenegro","C_RESID":"Reporting country","Year":2012,"Average":1461.1416666667},{"GEO":"North Macedonia","C_RESID":"Foreign country","Year":2012,"Average":null},{"GEO":"North Macedonia","C_RESID":"Reporting country","Year":2012,"Average":null},{"GEO":"Albania","C_RESID":"Foreign country","Year":2012,"Average":null},{"GEO":"Albania","C_RESID":"Reporting country","Year":2012,"Average":null},{"GEO":"Serbia","C_RESID":"Foreign country","Year":2012,"Average":6546.7916666667},{"GEO":"Serbia","C_RESID":"Reporting country","Year":2012,"Average":9900.7916666667},{"GEO":"Turkey","C_RESID":"Foreign country","Year":2012,"Average":null},{"GEO":"Turkey","C_RESID":"Reporting country","Year":2012,"Average":null},{"GEO":"Kosovo (under United Nations Security Council Resolution 1244\/99)","C_RESID":"Foreign country","Year":2012,"Average":null},{"GEO":"Kosovo (under United Nations Security Council Resolution 1244\/99)","C_RESID":"Reporting country","Year":2012,"Average":null},{"GEO":"Belgium","C_RESID":"Foreign country","Year":2013,"Average":63695.8083333333},{"GEO":"Belgium","C_RESID":"Reporting country","Year":2013,"Average":53747.0916666667},{"GEO":"Bulgaria","C_RESID":"Foreign country","Year":2013,"Average":23505.6083333333},{"GEO":"Bulgaria","C_RESID":"Reporting country","Year":2013,"Average":25221.8},{"GEO":"Czechia","C_RESID":"Foreign country","Year":2013,"Average":65432.2083333333},{"GEO":"Czechia","C_RESID":"Reporting country","Year":2013,"Average":62965.05},{"GEO":"Denmark","C_RESID":"Foreign country","Year":2013,"Average":19406.8166666667},{"GEO":"Denmark","C_RESID":"Reporting country","Year":2013,"Average":34234.975},{"GEO":"Germany (until 1990 former territory of the FRG)","C_RESID":"Foreign country","Year":2013,"Average":262067.0833333333},{"GEO":"Germany (until 1990 former territory of the FRG)","C_RESID":"Reporting country","Year":2013,"Average":985356.0666666667},{"GEO":"Estonia","C_RESID":"Foreign country","Year":2013,"Average":16307.2583333333},{"GEO":"Estonia","C_RESID":"Reporting country","Year":2013,"Average":8694.775},{"GEO":"Ireland","C_RESID":"Foreign country","Year":2013,"Average":null},{"GEO":"Ireland","C_RESID":"Reporting country","Year":2013,"Average":null},{"GEO":"Greece","C_RESID":"Foreign country","Year":2013,"Average":106244.9583333333},{"GEO":"Greece","C_RESID":"Reporting country","Year":2013,"Average":61382.1666666667},{"GEO":"Spain","C_RESID":"Foreign country","Year":2013,"Average":414990.6833333333},{"GEO":"Spain","C_RESID":"Reporting country","Year":2013,"Average":432285.0583333333},{"GEO":"France","C_RESID":"Foreign country","Year":2013,"Average":383345.775},{"GEO":"France","C_RESID":"Reporting country","Year":2013,"Average":897440.4},{"GEO":"Croatia","C_RESID":"Foreign country","Year":2013,"Average":89791.6666666667},{"GEO":"Croatia","C_RESID":"Reporting country","Year":2013,"Average":11922.5666666667},{"GEO":"Italy","C_RESID":"Foreign country","Year":2013,"Average":418860.3},{"GEO":"Italy","C_RESID":"Reporting country","Year":2013,"Average":446660.7833333333},{"GEO":"Cyprus","C_RESID":"Foreign country","Year":2013,"Average":16231.9583333333},{"GEO":"Cyprus","C_RESID":"Reporting country","Year":2013,"Average":3671.2666666667},{"GEO":"Latvia","C_RESID":"Foreign country","Year":2013,"Average":10415.1166666667},{"GEO":"Latvia","C_RESID":"Reporting country","Year":2013,"Average":4911.8916666667},{"GEO":"Lithuania","C_RESID":"Foreign country","Year":2013,"Average":10502.8},{"GEO":"Lithuania","C_RESID":"Reporting country","Year":2013,"Average":9999.2833333333},{"GEO":"Luxembourg","C_RESID":"Foreign country","Year":2013,"Average":7869.55},{"GEO":"Luxembourg","C_RESID":"Reporting country","Year":2013,"Average":833.25},{"GEO":"Hungary","C_RESID":"Foreign country","Year":2013,"Average":36564.1},{"GEO":"Hungary","C_RESID":"Reporting country","Year":2013,"Average":41081.275},{"GEO":"Malta","C_RESID":"Foreign country","Year":2013,"Average":10933.1833333333},{"GEO":"Malta","C_RESID":"Reporting country","Year":2013,"Average":1238.85},{"GEO":"Netherlands","C_RESID":"Foreign country","Year":2013,"Average":106524.1},{"GEO":"Netherlands","C_RESID":"Reporting country","Year":2013,"Average":177227.3583333333},{"GEO":"Austria","C_RESID":"Foreign country","Year":2013,"Average":181522.8083333333},{"GEO":"Austria","C_RESID":"Reporting country","Year":2013,"Average":92979.4},{"GEO":"Poland","C_RESID":"Foreign country","Year":2013,"Average":43691.4333333333},{"GEO":"Poland","C_RESID":"Reporting country","Year":2013,"Average":151318.05},{"GEO":"Portugal","C_RESID":"Foreign country","Year":2013,"Average":70002.1},{"GEO":"Portugal","C_RESID":"Reporting country","Year":2013,"Average":62508.375},{"GEO":"Romania","C_RESID":"Foreign country","Year":2013,"Average":14298.9083333333},{"GEO":"Romania","C_RESID":"Reporting country","Year":2013,"Average":51696.2333333333},{"GEO":"Slovenia","C_RESID":"Foreign country","Year":2013,"Average":18186.4916666667},{"GEO":"Slovenia","C_RESID":"Reporting country","Year":2013,"Average":9112.6916666667},{"GEO":"Slovakia","C_RESID":"Foreign country","Year":2013,"Average":13773.2166666667},{"GEO":"Slovakia","C_RESID":"Reporting country","Year":2013,"Average":19585.95},{"GEO":"Finland","C_RESID":"Foreign country","Year":2013,"Average":23322.3666666667},{"GEO":"Finland","C_RESID":"Reporting country","Year":2013,"Average":66897.4166666667},{"GEO":"Sweden","C_RESID":"Foreign country","Year":2013,"Average":41913.8},{"GEO":"Sweden","C_RESID":"Reporting country","Year":2013,"Average":163152.6416666667},{"GEO":"United Kingdom","C_RESID":"Foreign country","Year":2013,"Average":203309.55},{"GEO":"United Kingdom","C_RESID":"Reporting country","Year":2013,"Average":686678.8416666667},{"GEO":"Iceland","C_RESID":"Foreign country","Year":2013,"Average":15984.0083333333},{"GEO":"Iceland","C_RESID":"Reporting country","Year":2013,"Average":4708.1083333333},{"GEO":"Liechtenstein","C_RESID":"Foreign country","Year":2013,"Average":497.0},{"GEO":"Liechtenstein","C_RESID":"Reporting country","Year":2013,"Average":9.3666666667},{"GEO":"Norway","C_RESID":"Foreign country","Year":2013,"Average":39448.3083333333},{"GEO":"Norway","C_RESID":"Reporting country","Year":2013,"Average":118490.8666666667},{"GEO":"Switzerland","C_RESID":"Foreign country","Year":2013,"Average":null},{"GEO":"Switzerland","C_RESID":"Reporting country","Year":2013,"Average":null},{"GEO":"Montenegro","C_RESID":"Foreign country","Year":2013,"Average":11036.6916666667},{"GEO":"Montenegro","C_RESID":"Reporting country","Year":2013,"Average":1396.6916666667},{"GEO":"North Macedonia","C_RESID":"Foreign country","Year":2013,"Average":null},{"GEO":"North Macedonia","C_RESID":"Reporting country","Year":2013,"Average":null},{"GEO":"Albania","C_RESID":"Foreign country","Year":2013,"Average":null},{"GEO":"Albania","C_RESID":"Reporting country","Year":2013,"Average":null},{"GEO":"Serbia","C_RESID":"Foreign country","Year":2013,"Average":7554.78},{"GEO":"Serbia","C_RESID":"Reporting country","Year":2013,"Average":10443.49},{"GEO":"Turkey","C_RESID":"Foreign country","Year":2013,"Average":null},{"GEO":"Turkey","C_RESID":"Reporting country","Year":2013,"Average":null},{"GEO":"Kosovo (under United Nations Security Council Resolution 1244\/99)","C_RESID":"Foreign country","Year":2013,"Average":null},{"GEO":"Kosovo (under United Nations Security Council Resolution 1244\/99)","C_RESID":"Reporting country","Year":2013,"Average":null},{"GEO":"Belgium","C_RESID":"Foreign country","Year":2014,"Average":65752.3833333333},{"GEO":"Belgium","C_RESID":"Reporting country","Year":2014,"Average":56427.7083333333},{"GEO":"Bulgaria","C_RESID":"Foreign country","Year":2014,"Average":23263.15},{"GEO":"Bulgaria","C_RESID":"Reporting country","Year":2014,"Average":26286.0833333333},{"GEO":"Czechia","C_RESID":"Foreign country","Year":2014,"Average":67465.7083333333},{"GEO":"Czechia","C_RESID":"Reporting country","Year":2014,"Average":62426.5916666667},{"GEO":"Denmark","C_RESID":"Foreign country","Year":2014,"Average":20545.3916666667},{"GEO":"Denmark","C_RESID":"Reporting country","Year":2014,"Average":35358.45},{"GEO":"Germany (until 1990 former territory of the FRG)","C_RESID":"Foreign country","Year":2014,"Average":274108.475},{"GEO":"Germany (until 1990 former territory of the FRG)","C_RESID":"Reporting country","Year":2014,"Average":1019145.3666666666},{"GEO":"Estonia","C_RESID":"Foreign country","Year":2014,"Average":16527.625},{"GEO":"Estonia","C_RESID":"Reporting country","Year":2014,"Average":9197.9583333333},{"GEO":"Ireland","C_RESID":"Foreign country","Year":2014,"Average":19673.8416666667},{"GEO":"Ireland","C_RESID":"Reporting country","Year":2014,"Average":67027.8},{"GEO":"Greece","C_RESID":"Foreign country","Year":2014,"Average":120015.7666666667},{"GEO":"Greece","C_RESID":"Reporting country","Year":2014,"Average":61896.4583333333},{"GEO":"Spain","C_RESID":"Foreign country","Year":2014,"Average":436164.4},{"GEO":"Spain","C_RESID":"Reporting country","Year":2014,"Average":459383.4666666667},{"GEO":"France","C_RESID":"Foreign country","Year":2014,"Average":384044.075},{"GEO":"France","C_RESID":"Reporting country","Year":2014,"Average":890601.85},{"GEO":"Croatia","C_RESID":"Foreign country","Year":2014,"Average":95323.2833333333},{"GEO":"Croatia","C_RESID":"Reporting country","Year":2014,"Average":12033.4083333333},{"GEO":"Italy","C_RESID":"Foreign country","Year":2014,"Average":430295.8333333333},{"GEO":"Italy","C_RESID":"Reporting country","Year":2014,"Average":457640.4333333333},{"GEO":"Cyprus","C_RESID":"Foreign country","Year":2014,"Average":16130.3416666667},{"GEO":"Cyprus","C_RESID":"Reporting country","Year":2014,"Average":3616.5083333333},{"GEO":"Latvia","C_RESID":"Foreign country","Year":2014,"Average":11925.3166666667},{"GEO":"Latvia","C_RESID":"Reporting country","Year":2014,"Average":5561.1916666667},{"GEO":"Lithuania","C_RESID":"Foreign country","Year":2014,"Average":11306.9583333333},{"GEO":"Lithuania","C_RESID":"Reporting country","Year":2014,"Average":10972.4666666667},{"GEO":"Luxembourg","C_RESID":"Foreign country","Year":2014,"Average":8653.9583333333},{"GEO":"Luxembourg","C_RESID":"Reporting country","Year":2014,"Average":870.1416666667},{"GEO":"Hungary","C_RESID":"Foreign country","Year":2014,"Average":38481.2583333333},{"GEO":"Hungary","C_RESID":"Reporting country","Year":2014,"Average":45959.7083333333},{"GEO":"Malta","C_RESID":"Foreign country","Year":2014,"Average":11675.2666666667},{"GEO":"Malta","C_RESID":"Reporting country","Year":2014,"Average":1295.225},{"GEO":"Netherlands","C_RESID":"Foreign country","Year":2014,"Average":116663.225},{"GEO":"Netherlands","C_RESID":"Reporting country","Year":2014,"Average":184309.8916666667},{"GEO":"Austria","C_RESID":"Foreign country","Year":2014,"Average":185384.975},{"GEO":"Austria","C_RESID":"Reporting country","Year":2014,"Average":95003.2916666667},{"GEO":"Poland","C_RESID":"Foreign country","Year":2014,"Average":45586.125},{"GEO":"Poland","C_RESID":"Reporting country","Year":2014,"Average":163447.025},{"GEO":"Portugal","C_RESID":"Foreign country","Year":2014,"Average":81143.6416666667},{"GEO":"Portugal","C_RESID":"Reporting country","Year":2014,"Average":68756.4833333333},{"GEO":"Romania","C_RESID":"Foreign country","Year":2014,"Average":15931.8083333333},{"GEO":"Romania","C_RESID":"Reporting country","Year":2014,"Average":54435.1083333333},{"GEO":"Slovenia","C_RESID":"Foreign country","Year":2014,"Average":19265.475},{"GEO":"Slovenia","C_RESID":"Reporting country","Year":2014,"Average":8977.1166666667},{"GEO":"Slovakia","C_RESID":"Foreign country","Year":2014,"Average":12165.825},{"GEO":"Slovakia","C_RESID":"Reporting country","Year":2014,"Average":18578.4166666667},{"GEO":"Finland","C_RESID":"Foreign country","Year":2014,"Average":22760.4666666667},{"GEO":"Finland","C_RESID":"Reporting country","Year":2014,"Average":66073.75},{"GEO":"Sweden","C_RESID":"Foreign country","Year":2014,"Average":45461.3583333333},{"GEO":"Sweden","C_RESID":"Reporting country","Year":2014,"Average":169975.0416666667},{"GEO":"United Kingdom","C_RESID":"Foreign country","Year":2014,"Average":214419.5833333333},{"GEO":"United Kingdom","C_RESID":"Reporting country","Year":2014,"Average":640416.5833333333},{"GEO":"Iceland","C_RESID":"Foreign country","Year":2014,"Average":21639.5},{"GEO":"Iceland","C_RESID":"Reporting country","Year":2014,"Average":5831.1083333333},{"GEO":"Liechtenstein","C_RESID":"Foreign country","Year":2014,"Average":510.2833333333},{"GEO":"Liechtenstein","C_RESID":"Reporting country","Year":2014,"Average":8.7833333333},{"GEO":"Norway","C_RESID":"Foreign country","Year":2014,"Average":40095.1666666667},{"GEO":"Norway","C_RESID":"Reporting country","Year":2014,"Average":114749.1},{"GEO":"Switzerland","C_RESID":"Foreign country","Year":2014,"Average":null},{"GEO":"Switzerland","C_RESID":"Reporting country","Year":2014,"Average":null},{"GEO":"Montenegro","C_RESID":"Foreign country","Year":2014,"Average":11252.475},{"GEO":"Montenegro","C_RESID":"Reporting country","Year":2014,"Average":1392.325},{"GEO":"North Macedonia","C_RESID":"Foreign country","Year":2014,"Average":3475.75},{"GEO":"North Macedonia","C_RESID":"Reporting country","Year":2014,"Average":1729.7666666667},{"GEO":"Albania","C_RESID":"Foreign country","Year":2014,"Average":null},{"GEO":"Albania","C_RESID":"Reporting country","Year":2014,"Average":null},{"GEO":"Serbia","C_RESID":"Foreign country","Year":2014,"Average":8031.2},{"GEO":"Serbia","C_RESID":"Reporting country","Year":2014,"Average":9338.4272727273},{"GEO":"Turkey","C_RESID":"Foreign country","Year":2014,"Average":null},{"GEO":"Turkey","C_RESID":"Reporting country","Year":2014,"Average":null},{"GEO":"Kosovo (under United Nations Security Council Resolution 1244\/99)","C_RESID":"Foreign country","Year":2014,"Average":null},{"GEO":"Kosovo (under United Nations Security Council Resolution 1244\/99)","C_RESID":"Reporting country","Year":2014,"Average":null},{"GEO":"Belgium","C_RESID":"Foreign country","Year":2015,"Average":69622.9416666667},{"GEO":"Belgium","C_RESID":"Reporting country","Year":2015,"Average":62434.775},{"GEO":"Bulgaria","C_RESID":"Foreign country","Year":2015,"Average":23869.7583333333},{"GEO":"Bulgaria","C_RESID":"Reporting country","Year":2015,"Average":28455.5416666667},{"GEO":"Czechia","C_RESID":"Foreign country","Year":2015,"Average":72583.0},{"GEO":"Czechia","C_RESID":"Reporting country","Year":2015,"Average":70674.8833333333},{"GEO":"Denmark","C_RESID":"Foreign country","Year":2015,"Average":21924.4833333333},{"GEO":"Denmark","C_RESID":"Reporting country","Year":2015,"Average":37780.55},{"GEO":"Germany (until 1990 former territory of the FRG)","C_RESID":"Foreign country","Year":2015,"Average":290395.05},{"GEO":"Germany (until 1990 former territory of the FRG)","C_RESID":"Reporting country","Year":2015,"Average":1052633.4166666665},{"GEO":"Estonia","C_RESID":"Foreign country","Year":2015,"Average":16076.3416666667},{"GEO":"Estonia","C_RESID":"Reporting country","Year":2015,"Average":9858.1583333333},{"GEO":"Ireland","C_RESID":"Foreign country","Year":2015,"Average":null},{"GEO":"Ireland","C_RESID":"Reporting country","Year":2015,"Average":null},{"GEO":"Greece","C_RESID":"Foreign country","Year":2015,"Average":129170.5916666667},{"GEO":"Greece","C_RESID":"Reporting country","Year":2015,"Average":63328.1083333333},{"GEO":"Spain","C_RESID":"Foreign country","Year":2015,"Average":461385.0583333333},{"GEO":"Spain","C_RESID":"Reporting country","Year":2015,"Average":490856.1333333333},{"GEO":"France","C_RESID":"Foreign country","Year":2015,"Average":390455.0},{"GEO":"France","C_RESID":"Reporting country","Year":2015,"Average":922755.05},{"GEO":"Croatia","C_RESID":"Foreign country","Year":2015,"Average":104529.2416666667},{"GEO":"Croatia","C_RESID":"Reporting country","Year":2015,"Average":13445.975},{"GEO":"Italy","C_RESID":"Foreign country","Year":2015,"Average":458660.425},{"GEO":"Italy","C_RESID":"Reporting country","Year":2015,"Average":486274.05},{"GEO":"Cyprus","C_RESID":"Foreign country","Year":2015,"Average":15619.35},{"GEO":"Cyprus","C_RESID":"Reporting country","Year":2015,"Average":3679.6},{"GEO":"Latvia","C_RESID":"Foreign country","Year":2015,"Average":12289.7083333333},{"GEO":"Latvia","C_RESID":"Reporting country","Year":2015,"Average":5538.5666666667},{"GEO":"Lithuania","C_RESID":"Foreign country","Year":2015,"Average":11570.725},{"GEO":"Lithuania","C_RESID":"Reporting country","Year":2015,"Average":11811.0083333333},{"GEO":"Luxembourg","C_RESID":"Foreign country","Year":2015,"Average":9079.8},{"GEO":"Luxembourg","C_RESID":"Reporting country","Year":2015,"Average":887.8416666667},{"GEO":"Hungary","C_RESID":"Foreign country","Year":2015,"Average":41070.925},{"GEO":"Hungary","C_RESID":"Reporting country","Year":2015,"Average":49872.825},{"GEO":"Malta","C_RESID":"Foreign country","Year":2015,"Average":11906.6666666667},{"GEO":"Malta","C_RESID":"Reporting country","Year":2015,"Average":1310.5583333333},{"GEO":"Netherlands","C_RESID":"Foreign country","Year":2015,"Average":123765.1416666667},{"GEO":"Netherlands","C_RESID":"Reporting country","Year":2015,"Average":186577.3333333333},{"GEO":"Austria","C_RESID":"Foreign country","Year":2015,"Average":196254.25},{"GEO":"Austria","C_RESID":"Reporting country","Year":2015,"Average":98387.6333333333},{"GEO":"Poland","C_RESID":"Foreign country","Year":2015,"Average":49148.3636363636},{"GEO":"Poland","C_RESID":"Reporting country","Year":2015,"Average":177104.05},{"GEO":"Portugal","C_RESID":"Foreign country","Year":2015,"Average":83041.7333333333},{"GEO":"Portugal","C_RESID":"Reporting country","Year":2015,"Average":67964.4},{"GEO":"Romania","C_RESID":"Foreign country","Year":2015,"Average":18603.0916666667},{"GEO":"Romania","C_RESID":"Reporting country","Year":2015,"Average":63861.9166666667},{"GEO":"Slovenia","C_RESID":"Foreign country","Year":2015,"Average":21524.1166666667},{"GEO":"Slovenia","C_RESID":"Reporting country","Year":2015,"Average":9826.025},{"GEO":"Slovakia","C_RESID":"Foreign country","Year":2015,"Average":14222.525},{"GEO":"Slovakia","C_RESID":"Reporting country","Year":2015,"Average":21310.5916666667},{"GEO":"Finland","C_RESID":"Foreign country","Year":2015,"Average":21850.325},{"GEO":"Finland","C_RESID":"Reporting country","Year":2015,"Average":67606.6833333333},{"GEO":"Sweden","C_RESID":"Foreign country","Year":2015,"Average":50769.0416666667},{"GEO":"Sweden","C_RESID":"Reporting country","Year":2015,"Average":178333.225},{"GEO":"United Kingdom","C_RESID":"Foreign country","Year":2015,"Average":368950.9916666666},{"GEO":"United Kingdom","C_RESID":"Reporting country","Year":2015,"Average":667801.25},{"GEO":"Iceland","C_RESID":"Foreign country","Year":2015,"Average":28869.3166666667},{"GEO":"Iceland","C_RESID":"Reporting country","Year":2015,"Average":5116.1833333333},{"GEO":"Liechtenstein","C_RESID":"Foreign country","Year":2015,"Average":472.2166666667},{"GEO":"Liechtenstein","C_RESID":"Reporting country","Year":2015,"Average":8.1916666667},{"GEO":"Norway","C_RESID":"Foreign country","Year":2015,"Average":43266.25},{"GEO":"Norway","C_RESID":"Reporting country","Year":2015,"Average":116413.1083333333},{"GEO":"Switzerland","C_RESID":"Foreign country","Year":2015,"Average":null},{"GEO":"Switzerland","C_RESID":"Reporting country","Year":2015,"Average":null},{"GEO":"Montenegro","C_RESID":"Foreign country","Year":2015,"Average":null},{"GEO":"Montenegro","C_RESID":"Reporting country","Year":2015,"Average":null},{"GEO":"North Macedonia","C_RESID":"Foreign country","Year":2015,"Average":3992.9333333333},{"GEO":"North Macedonia","C_RESID":"Reporting country","Year":2015,"Average":1829.4333333333},{"GEO":"Albania","C_RESID":"Foreign country","Year":2015,"Average":null},{"GEO":"Albania","C_RESID":"Reporting country","Year":2015,"Average":null},{"GEO":"Serbia","C_RESID":"Foreign country","Year":2015,"Average":9285.6833333333},{"GEO":"Serbia","C_RESID":"Reporting country","Year":2015,"Average":10413.4166666667},{"GEO":"Turkey","C_RESID":"Foreign country","Year":2015,"Average":null},{"GEO":"Turkey","C_RESID":"Reporting country","Year":2015,"Average":null},{"GEO":"Kosovo (under United Nations Security Council Resolution 1244\/99)","C_RESID":"Foreign country","Year":2015,"Average":null},{"GEO":"Kosovo (under United Nations Security Council Resolution 1244\/99)","C_RESID":"Reporting country","Year":2015,"Average":null},{"GEO":"Belgium","C_RESID":"Foreign country","Year":2016,"Average":62648.1666666667},{"GEO":"Belgium","C_RESID":"Reporting country","Year":2016,"Average":65365.8416666667},{"GEO":"Bulgaria","C_RESID":"Foreign country","Year":2016,"Average":28224.4333333333},{"GEO":"Bulgaria","C_RESID":"Reporting country","Year":2016,"Average":31745.5416666667},{"GEO":"Czechia","C_RESID":"Foreign country","Year":2016,"Average":77678.6666666667},{"GEO":"Czechia","C_RESID":"Reporting country","Year":2016,"Average":75561.775},{"GEO":"Denmark","C_RESID":"Foreign country","Year":2016,"Average":22842.4416666667},{"GEO":"Denmark","C_RESID":"Reporting country","Year":2016,"Average":39511.925},{"GEO":"Germany (until 1990 former territory of the FRG)","C_RESID":"Foreign country","Year":2016,"Average":295041.0333333333},{"GEO":"Germany (until 1990 former territory of the FRG)","C_RESID":"Reporting country","Year":2016,"Average":1085157.075},{"GEO":"Estonia","C_RESID":"Foreign country","Year":2016,"Average":17137.7166666667},{"GEO":"Estonia","C_RESID":"Reporting country","Year":2016,"Average":10569.9},{"GEO":"Ireland","C_RESID":"Foreign country","Year":2016,"Average":null},{"GEO":"Ireland","C_RESID":"Reporting country","Year":2016,"Average":null},{"GEO":"Greece","C_RESID":"Foreign country","Year":2016,"Average":130534.0916666667},{"GEO":"Greece","C_RESID":"Reporting country","Year":2016,"Average":67080.7166666667},{"GEO":"Spain","C_RESID":"Foreign country","Year":2016,"Average":511182.0},{"GEO":"Spain","C_RESID":"Reporting country","Year":2016,"Average":518332.825},{"GEO":"France","C_RESID":"Foreign country","Year":2016,"Average":375017.5416666666},{"GEO":"France","C_RESID":"Reporting country","Year":2016,"Average":936074.1333333334},{"GEO":"Croatia","C_RESID":"Foreign country","Year":2016,"Average":114228.7},{"GEO":"Croatia","C_RESID":"Reporting country","Year":2016,"Average":14492.8916666667},{"GEO":"Italy","C_RESID":"Foreign country","Year":2016,"Average":473035.325},{"GEO":"Italy","C_RESID":"Reporting country","Year":2016,"Average":501500.0333333333},{"GEO":"Cyprus","C_RESID":"Foreign country","Year":2016,"Average":18901.4666666667},{"GEO":"Cyprus","C_RESID":"Reporting country","Year":2016,"Average":3848.2083333333},{"GEO":"Latvia","C_RESID":"Foreign country","Year":2016,"Average":13113.6},{"GEO":"Latvia","C_RESID":"Reporting country","Year":2016,"Average":6083.425},{"GEO":"Lithuania","C_RESID":"Foreign country","Year":2016,"Average":12649.0833333333},{"GEO":"Lithuania","C_RESID":"Reporting country","Year":2016,"Average":12888.5333333333},{"GEO":"Luxembourg","C_RESID":"Foreign country","Year":2016,"Average":8780.4416666667},{"GEO":"Luxembourg","C_RESID":"Reporting country","Year":2016,"Average":901.0916666667},{"GEO":"Hungary","C_RESID":"Foreign country","Year":2016,"Average":44182.025},{"GEO":"Hungary","C_RESID":"Reporting country","Year":2016,"Average":52885.8416666667},{"GEO":"Malta","C_RESID":"Foreign country","Year":2016,"Average":12234.5333333333},{"GEO":"Malta","C_RESID":"Reporting country","Year":2016,"Average":1261.575},{"GEO":"Netherlands","C_RESID":"Foreign country","Year":2016,"Average":131912.3166666667},{"GEO":"Netherlands","C_RESID":"Reporting country","Year":2016,"Average":192113.1416666667},{"GEO":"Austria","C_RESID":"Foreign country","Year":2016,"Average":205646.6333333333},{"GEO":"Austria","C_RESID":"Reporting country","Year":2016,"Average":103442.9583333333},{"GEO":"Poland","C_RESID":"Foreign country","Year":2016,"Average":53156.6083333333},{"GEO":"Poland","C_RESID":"Reporting country","Year":2016,"Average":197745.9583333333},{"GEO":"Portugal","C_RESID":"Foreign country","Year":2016,"Average":102866.5166666667},{"GEO":"Portugal","C_RESID":"Reporting country","Year":2016,"Average":79774.3083333333},{"GEO":"Romania","C_RESID":"Foreign country","Year":2016,"Average":20595.1},{"GEO":"Romania","C_RESID":"Reporting country","Year":2016,"Average":70382.9083333333},{"GEO":"Slovenia","C_RESID":"Foreign country","Year":2016,"Average":23974.7833333333},{"GEO":"Slovenia","C_RESID":"Reporting country","Year":2016,"Average":10330.7166666667},{"GEO":"Slovakia","C_RESID":"Foreign country","Year":2016,"Average":16631.7},{"GEO":"Slovakia","C_RESID":"Reporting country","Year":2016,"Average":24570.8166666667},{"GEO":"Finland","C_RESID":"Foreign country","Year":2016,"Average":23240.8583333333},{"GEO":"Finland","C_RESID":"Reporting country","Year":2016,"Average":69326.5},{"GEO":"Sweden","C_RESID":"Foreign country","Year":2016,"Average":54660.4416666667},{"GEO":"Sweden","C_RESID":"Reporting country","Year":2016,"Average":187830.225},{"GEO":"United Kingdom","C_RESID":"Foreign country","Year":2016,"Average":362246.7},{"GEO":"United Kingdom","C_RESID":"Reporting country","Year":2016,"Average":654762.25},{"GEO":"Iceland","C_RESID":"Foreign country","Year":2016,"Average":35238.9833333333},{"GEO":"Iceland","C_RESID":"Reporting country","Year":2016,"Average":5758.4},{"GEO":"Liechtenstein","C_RESID":"Foreign country","Year":2016,"Average":575.7},{"GEO":"Liechtenstein","C_RESID":"Reporting country","Year":2016,"Average":13.9166666667},{"GEO":"Norway","C_RESID":"Foreign country","Year":2016,"Average":48626.1166666667},{"GEO":"Norway","C_RESID":"Reporting country","Year":2016,"Average":120686.2},{"GEO":"Switzerland","C_RESID":"Foreign country","Year":2016,"Average":86548.9666666667},{"GEO":"Switzerland","C_RESID":"Reporting country","Year":2016,"Average":92801.4333333333},{"GEO":"Montenegro","C_RESID":"Foreign country","Year":2016,"Average":null},{"GEO":"Montenegro","C_RESID":"Reporting country","Year":2016,"Average":null},{"GEO":"North Macedonia","C_RESID":"Foreign country","Year":2016,"Average":4234.8333333333},{"GEO":"North Macedonia","C_RESID":"Reporting country","Year":2016,"Average":1983.1166666667},{"GEO":"Albania","C_RESID":"Foreign country","Year":2016,"Average":null},{"GEO":"Albania","C_RESID":"Reporting country","Year":2016,"Average":null},{"GEO":"Serbia","C_RESID":"Foreign country","Year":2016,"Average":10649.6333333333},{"GEO":"Serbia","C_RESID":"Reporting country","Year":2016,"Average":12046.7333333333},{"GEO":"Turkey","C_RESID":"Foreign country","Year":2016,"Average":null},{"GEO":"Turkey","C_RESID":"Reporting country","Year":2016,"Average":null},{"GEO":"Kosovo (under United Nations Security Council Resolution 1244\/99)","C_RESID":"Foreign country","Year":2016,"Average":null},{"GEO":"Kosovo (under United Nations Security Council Resolution 1244\/99)","C_RESID":"Reporting country","Year":2016,"Average":null},{"GEO":"Belgium","C_RESID":"Foreign country","Year":2017,"Average":69871.4416666667},{"GEO":"Belgium","C_RESID":"Reporting country","Year":2017,"Average":66122.3666666667},{"GEO":"Bulgaria","C_RESID":"Foreign country","Year":2017,"Average":30465.25},{"GEO":"Bulgaria","C_RESID":"Reporting country","Year":2017,"Average":31715.1333333333},{"GEO":"Czechia","C_RESID":"Foreign country","Year":2017,"Average":84670.5666666667},{"GEO":"Czechia","C_RESID":"Reporting country","Year":2017,"Average":82000.775},{"GEO":"Denmark","C_RESID":"Foreign country","Year":2017,"Average":23990.5583333333},{"GEO":"Denmark","C_RESID":"Reporting country","Year":2017,"Average":40117.625},{"GEO":"Germany (until 1990 former territory of the FRG)","C_RESID":"Foreign country","Year":2017,"Average":310910.725},{"GEO":"Germany (until 1990 former territory of the FRG)","C_RESID":"Reporting country","Year":2017,"Average":1125088.2583333333},{"GEO":"Estonia","C_RESID":"Foreign country","Year":2017,"Average":18170.2090909091},{"GEO":"Estonia","C_RESID":"Reporting country","Year":2017,"Average":11726.3272727273},{"GEO":"Ireland","C_RESID":"Foreign country","Year":2017,"Average":30322.8333333333},{"GEO":"Ireland","C_RESID":"Reporting country","Year":2017,"Average":65694.225},{"GEO":"Greece","C_RESID":"Foreign country","Year":2017,"Average":149408.55},{"GEO":"Greece","C_RESID":"Reporting country","Year":2017,"Average":68390.7916666667},{"GEO":"Spain","C_RESID":"Foreign country","Year":2017,"Average":543548.1666666667},{"GEO":"Spain","C_RESID":"Reporting country","Year":2017,"Average":534477.6166666667},{"GEO":"France","C_RESID":"Foreign country","Year":2017,"Average":407665.6666666666},{"GEO":"France","C_RESID":"Reporting country","Year":2017,"Average":982632.7166666666},{"GEO":"Croatia","C_RESID":"Foreign country","Year":2017,"Average":129847.5333333333},{"GEO":"Croatia","C_RESID":"Reporting country","Year":2017,"Average":15235.275},{"GEO":"Italy","C_RESID":"Foreign country","Year":2017,"Average":504359.9166666667},{"GEO":"Italy","C_RESID":"Reporting country","Year":2017,"Average":522269.7166666667},{"GEO":"Cyprus","C_RESID":"Foreign country","Year":2017,"Average":20738.425},{"GEO":"Cyprus","C_RESID":"Reporting country","Year":2017,"Average":3815.4},{"GEO":"Latvia","C_RESID":"Foreign country","Year":2017,"Average":14824.775},{"GEO":"Latvia","C_RESID":"Reporting country","Year":2017,"Average":6653.0416666667},{"GEO":"Lithuania","C_RESID":"Foreign country","Year":2017,"Average":13198.3416666667},{"GEO":"Lithuania","C_RESID":"Reporting country","Year":2017,"Average":13911.6916666667},{"GEO":"Luxembourg","C_RESID":"Foreign country","Year":2017,"Average":8715.6916666667},{"GEO":"Luxembourg","C_RESID":"Reporting country","Year":2017,"Average":917.2916666667},{"GEO":"Hungary","C_RESID":"Foreign country","Year":2017,"Average":47083.975},{"GEO":"Hungary","C_RESID":"Reporting country","Year":2017,"Average":56744.7666666667},{"GEO":"Malta","C_RESID":"Foreign country","Year":2017,"Average":13852.975},{"GEO":"Malta","C_RESID":"Reporting country","Year":2017,"Average":1392.5583333333},{"GEO":"Netherlands","C_RESID":"Foreign country","Year":2017,"Average":149368.1583333333},{"GEO":"Netherlands","C_RESID":"Reporting country","Year":2017,"Average":202591.175},{"GEO":"Austria","C_RESID":"Foreign country","Year":2017,"Average":215883.375},{"GEO":"Austria","C_RESID":"Reporting country","Year":2017,"Average":105671.8083333333},{"GEO":"Poland","C_RESID":"Foreign country","Year":2017,"Average":56697.225},{"GEO":"Poland","C_RESID":"Reporting country","Year":2017,"Average":209880.6416666667},{"GEO":"Portugal","C_RESID":"Foreign country","Year":2017,"Average":119164.7583333333},{"GEO":"Portugal","C_RESID":"Reporting country","Year":2017,"Average":85481.3666666667},{"GEO":"Romania","C_RESID":"Foreign country","Year":2017,"Average":22910.6},{"GEO":"Romania","C_RESID":"Reporting country","Year":2017,"Average":77558.3666666667},{"GEO":"Slovenia","C_RESID":"Foreign country","Year":2017,"Average":28022.15},{"GEO":"Slovenia","C_RESID":"Reporting country","Year":2017,"Average":10912.7333333333},{"GEO":"Slovakia","C_RESID":"Foreign country","Year":2017,"Average":17745.8916666667},{"GEO":"Slovakia","C_RESID":"Reporting country","Year":2017,"Average":26318.8833333333},{"GEO":"Finland","C_RESID":"Foreign country","Year":2017,"Average":26502.1166666667},{"GEO":"Finland","C_RESID":"Reporting country","Year":2017,"Average":71784.5},{"GEO":"Sweden","C_RESID":"Foreign country","Year":2017,"Average":57208.3},{"GEO":"Sweden","C_RESID":"Reporting country","Year":2017,"Average":190228.5166666667},{"GEO":"United Kingdom","C_RESID":"Foreign country","Year":2017,"Average":234437.075},{"GEO":"United Kingdom","C_RESID":"Reporting country","Year":2017,"Average":676360.6333333333},{"GEO":"Iceland","C_RESID":"Foreign country","Year":2017,"Average":39523.0833333333},{"GEO":"Iceland","C_RESID":"Reporting country","Year":2017,"Average":5932.1},{"GEO":"Liechtenstein","C_RESID":"Foreign country","Year":2017,"Average":660.5166666667},{"GEO":"Liechtenstein","C_RESID":"Reporting country","Year":2017,"Average":13.975},{"GEO":"Norway","C_RESID":"Foreign country","Year":2017,"Average":48709.5583333333},{"GEO":"Norway","C_RESID":"Reporting country","Year":2017,"Average":107743.7333333333},{"GEO":"Switzerland","C_RESID":"Foreign country","Year":2017,"Average":92643.2583333333},{"GEO":"Switzerland","C_RESID":"Reporting country","Year":2017,"Average":97394.675},{"GEO":"Montenegro","C_RESID":"Foreign country","Year":2017,"Average":7030.075},{"GEO":"Montenegro","C_RESID":"Reporting country","Year":2017,"Average":932.4166666667},{"GEO":"North Macedonia","C_RESID":"Foreign country","Year":2017,"Average":5207.1083333333},{"GEO":"North Macedonia","C_RESID":"Reporting country","Year":2017,"Average":1989.3916666667},{"GEO":"Albania","C_RESID":"Foreign country","Year":2017,"Average":11591.3714285714},{"GEO":"Albania","C_RESID":"Reporting country","Year":2017,"Average":5711.8285714286},{"GEO":"Serbia","C_RESID":"Foreign country","Year":2017,"Average":12469.175},{"GEO":"Serbia","C_RESID":"Reporting country","Year":2017,"Average":13152.85},{"GEO":"Turkey","C_RESID":"Foreign country","Year":2017,"Average":null},{"GEO":"Turkey","C_RESID":"Reporting country","Year":2017,"Average":null},{"GEO":"Kosovo (under United Nations Security Council Resolution 1244\/99)","C_RESID":"Foreign country","Year":2017,"Average":1084.5333333333},{"GEO":"Kosovo (under United Nations Security Council Resolution 1244\/99)","C_RESID":"Reporting country","Year":2017,"Average":510.575},{"GEO":"Belgium","C_RESID":"Foreign country","Year":2018,"Average":75931.5583333333},{"GEO":"Belgium","C_RESID":"Reporting country","Year":2018,"Average":70333.4166666667},{"GEO":"Bulgaria","C_RESID":"Foreign country","Year":2018,"Average":32584.6583333333},{"GEO":"Bulgaria","C_RESID":"Reporting country","Year":2018,"Average":32412.675},{"GEO":"Czechia","C_RESID":"Foreign country","Year":2018,"Average":88428.2833333333},{"GEO":"Czechia","C_RESID":"Reporting country","Year":2018,"Average":88631.3},{"GEO":"Denmark","C_RESID":"Foreign country","Year":2018,"Average":25247.5333333333},{"GEO":"Denmark","C_RESID":"Reporting country","Year":2018,"Average":41055.6166666667},{"GEO":"Germany (until 1990 former territory of the FRG)","C_RESID":"Foreign country","Year":2018,"Average":322703.2416666666},{"GEO":"Germany (until 1990 former territory of the FRG)","C_RESID":"Reporting country","Year":2018,"Average":1171484.8166666667},{"GEO":"Estonia","C_RESID":"Foreign country","Year":2018,"Average":17837.7916666667},{"GEO":"Estonia","C_RESID":"Reporting country","Year":2018,"Average":12091.3333333333},{"GEO":"Ireland","C_RESID":"Foreign country","Year":2018,"Average":28136.325},{"GEO":"Ireland","C_RESID":"Reporting country","Year":2018,"Average":66928.3},{"GEO":"Greece","C_RESID":"Foreign country","Year":2018,"Average":156522.5583333333},{"GEO":"Greece","C_RESID":"Reporting country","Year":2018,"Average":64923.6583333333},{"GEO":"Spain","C_RESID":"Foreign country","Year":2018,"Average":548300.6833333333},{"GEO":"Spain","C_RESID":"Reporting country","Year":2018,"Average":541623.5583333333},{"GEO":"France","C_RESID":"Foreign country","Year":2018,"Average":437549.075},{"GEO":"France","C_RESID":"Reporting country","Year":2018,"Average":991416.6666666666},{"GEO":"Croatia","C_RESID":"Foreign country","Year":2018,"Average":138624.9416666667},{"GEO":"Croatia","C_RESID":"Reporting country","Year":2018,"Average":16782.2833333333},{"GEO":"Italy","C_RESID":"Foreign country","Year":2018,"Average":509173.8333333333},{"GEO":"Italy","C_RESID":"Reporting country","Year":2018,"Average":525057.9833333333},{"GEO":"Cyprus","C_RESID":"Foreign country","Year":2018,"Average":22706.2833333333},{"GEO":"Cyprus","C_RESID":"Reporting country","Year":2018,"Average":4345.1916666667},{"GEO":"Latvia","C_RESID":"Foreign country","Year":2018,"Average":16044.975},{"GEO":"Latvia","C_RESID":"Reporting country","Year":2018,"Average":7361.7583333333},{"GEO":"Lithuania","C_RESID":"Foreign country","Year":2018,"Average":14497.4416666667},{"GEO":"Lithuania","C_RESID":"Reporting country","Year":2018,"Average":15321.9166666667},{"GEO":"Luxembourg","C_RESID":"Foreign country","Year":2018,"Average":8481.1083333333},{"GEO":"Luxembourg","C_RESID":"Reporting country","Year":2018,"Average":1010.8666666667},{"GEO":"Hungary","C_RESID":"Foreign country","Year":2018,"Average":49542.6916666667},{"GEO":"Hungary","C_RESID":"Reporting country","Year":2018,"Average":59757.775},{"GEO":"Malta","C_RESID":"Foreign country","Year":2018,"Average":15450.1272727273},{"GEO":"Malta","C_RESID":"Reporting country","Year":2018,"Average":1474.4636363636},{"GEO":"Netherlands","C_RESID":"Foreign country","Year":2018,"Average":158446.7},{"GEO":"Netherlands","C_RESID":"Reporting country","Year":2018,"Average":211162.3666666666},{"GEO":"Austria","C_RESID":"Foreign country","Year":2018,"Average":225051.725},{"GEO":"Austria","C_RESID":"Reporting country","Year":2018,"Average":109060.6083333333},{"GEO":"Poland","C_RESID":"Foreign country","Year":2018,"Average":59018.5916666667},{"GEO":"Poland","C_RESID":"Reporting country","Year":2018,"Average":223447.4916666666},{"GEO":"Portugal","C_RESID":"Foreign country","Year":2018,"Average":123232.9},{"GEO":"Portugal","C_RESID":"Reporting country","Year":2018,"Average":89331.45},{"GEO":"Romania","C_RESID":"Foreign country","Year":2018,"Average":23211.7083333333},{"GEO":"Romania","C_RESID":"Reporting country","Year":2018,"Average":83537.35},{"GEO":"Slovenia","C_RESID":"Foreign country","Year":2018,"Average":null},{"GEO":"Slovenia","C_RESID":"Reporting country","Year":2018,"Average":null},{"GEO":"Slovakia","C_RESID":"Foreign country","Year":2018,"Average":18449.8583333333},{"GEO":"Slovakia","C_RESID":"Reporting country","Year":2018,"Average":27276.8666666667},{"GEO":"Finland","C_RESID":"Foreign country","Year":2018,"Average":26875.425},{"GEO":"Finland","C_RESID":"Reporting country","Year":2018,"Average":72836.8},{"GEO":"Sweden","C_RESID":"Foreign country","Year":2018,"Average":60688.5333333333},{"GEO":"Sweden","C_RESID":"Reporting country","Year":2018,"Average":196334.65},{"GEO":"United Kingdom","C_RESID":"Foreign country","Year":2018,"Average":242069.0272727273},{"GEO":"United Kingdom","C_RESID":"Reporting country","Year":2018,"Average":712223.2272727273},{"GEO":"Iceland","C_RESID":"Foreign country","Year":2018,"Average":40277.1666666667},{"GEO":"Iceland","C_RESID":"Reporting country","Year":2018,"Average":6557.1666666667},{"GEO":"Liechtenstein","C_RESID":"Foreign country","Year":2018,"Average":707.2},{"GEO":"Liechtenstein","C_RESID":"Reporting country","Year":2018,"Average":14.85},{"GEO":"Norway","C_RESID":"Foreign country","Year":2018,"Average":47396.2666666667},{"GEO":"Norway","C_RESID":"Reporting country","Year":2018,"Average":107007.2916666667},{"GEO":"Switzerland","C_RESID":"Foreign country","Year":2018,"Average":105330.4888888889},{"GEO":"Switzerland","C_RESID":"Reporting country","Year":2018,"Average":109055.0777777778},{"GEO":"Montenegro","C_RESID":"Foreign country","Year":2018,"Average":7992.675},{"GEO":"Montenegro","C_RESID":"Reporting country","Year":2018,"Average":981.0583333333},{"GEO":"North Macedonia","C_RESID":"Foreign country","Year":2018,"Average":5856.9416666667},{"GEO":"North Macedonia","C_RESID":"Reporting country","Year":2018,"Average":2238.4333333333},{"GEO":"Albania","C_RESID":"Foreign country","Year":2018,"Average":2828.125},{"GEO":"Albania","C_RESID":"Reporting country","Year":2018,"Average":2582.825},{"GEO":"Serbia","C_RESID":"Foreign country","Year":2018,"Average":14249.675},{"GEO":"Serbia","C_RESID":"Reporting country","Year":2018,"Average":14183.15},{"GEO":"Turkey","C_RESID":"Foreign country","Year":2018,"Average":null},{"GEO":"Turkey","C_RESID":"Reporting country","Year":2018,"Average":null},{"GEO":"Kosovo (under United Nations Security Council Resolution 1244\/99)","C_RESID":"Foreign country","Year":2018,"Average":1069.5333333333},{"GEO":"Kosovo (under United Nations Security Council Resolution 1244\/99)","C_RESID":"Reporting country","Year":2018,"Average":548.4416666667}]